servers/__init__.py
servers/_version.py
servers/base_mcp_server.py
servers/appstoreconnect/__init__.py
servers/appstoreconnect/appstore_client.py
servers/appstoreconnect/appstore_connect_mcp_server.py
servers/appstoreconnect/models.py
servers/ssh/__init__.py
servers/ssh/models.py
servers/ssh/ssh_client.py
servers/ssh/ssh_mcp_server.py
pero_mcp_server-0.1.0.dist-info/METADATA
pero_mcp_server-0.1.0.dist-info/WHEEL
pero_mcp_server-0.1.0.dist-info/entry_points.txt
pero_mcp_server-0.1.0.dist-info/top_level.txt
pero_mcp_server-0.1.0.dist-info/RECORD
