Metadata-Version: 2.4
Name: pero-mcp-server
Version: 0.1.0
Summary: A comprehensive MCP (Model Context Protocol) server supporting App Store Connect and SSH operations
Author-email: peropero <tech@peropero.net>
License-Expression: MIT
Project-URL: Homepage, https://github.com/peroperogames/pero-mcp-server
Project-URL: Documentation, https://github.com/peroperogames/pero-mcp-server#readme
Project-URL: Repository, https://github.com/peroperogames/pero-mcp-server
Project-URL: Bug Tracker, https://github.com/peroperogames/pero-mcp-server/issues
Keywords: mcp,app-store-connect,ssh,automation,api
Classifier: Development Status :: 3 - Alpha
Classifier: Intended Audience :: Developers
Classifier: Programming Language :: Python :: 3
Classifier: Programming Language :: Python :: 3.8
Classifier: Programming Language :: Python :: 3.9
Classifier: Programming Language :: Python :: 3.10
Classifier: Programming Language :: Python :: 3.11
Classifier: Programming Language :: Python :: 3.12
Classifier: Topic :: Software Development :: Libraries :: Python Modules
Classifier: Topic :: System :: Systems Administration
Requires-Python: >=3.8
Requires-Dist: fastmcp>=0.1.0
Requires-Dist: paramiko>=2.9.0
Requires-Dist: requests>=2.25.0
Requires-Dist: cryptography>=3.4.0
Requires-Dist: pydantic>=1.8.0
Requires-Dist: python-dotenv>=0.19.0
Requires-Dist: PyJWT>=2.0.0
Provides-Extra: dev
Requires-Dist: pytest>=6.0; extra == "dev"
Requires-Dist: pytest-cov; extra == "dev"
Requires-Dist: black; extra == "dev"
Requires-Dist: flake8; extra == "dev"
Requires-Dist: mypy; extra == "dev"
